tmtools/__init__.py
tmtools/_bindings.cp312-win32.pyd
tmtools/helpers.py
tmtools/io.py
tmtools/testing.py
tmtools/data/2gtl.cif
tmtools/data/2gtl.pdb
tmtools/data/7ok9.cif
tmtools/data/7ok9.pdb
tmtools/tests/__init__.py
tmtools/tests/test_bindings.py
tmtools/tests/test_helpers.py
tmtools/tests/test_io.py
tmtools-0.3.0.dist-info/licenses/LICENSE.txt
tmtools-0.3.0.dist-info/METADATA
tmtools-0.3.0.dist-info/WHEEL
tmtools-0.3.0.dist-info/top_level.txt
tmtools-0.3.0.dist-info/RECORD
